{"trial_id": "1", "hyperparameters": {"space": [{"class_name": "Int", "config": {"name": "units_1", "default": null, "conditions": [], "min_value": 32, "max_value": 256, "step": 32, "sampling": "linear"}}, {"class_name": "Int", "config": {"name": "units_2", "default": null, "conditions": [], "min_value": 32, "max_value": 256, "step": 32, "sampling": "linear"}}, {"class_name": "Int", "config": {"name": "units_3", "default": null, "conditions": [], "min_value": 32, "max_value": 256, "step": 32, "sampling": "linear"}}], "values": {"units_1": 64, "units_2": 128, "units_3": 160}}, "metrics": {"metrics": {"loss": {"direction": "min", "observations": [{"value": [0.06605057269334794], "step": 95}]}, "mean_absolute_error": {"direction": "min", "observations": [{"value": [0.09203199148178101], "step": 95}]}, "val_loss": {"direction": "min", "observations": [{"value": [0.06717563569545745], "step": 95}]}, "val_mean_absolute_error": {"direction": "min", "observations": [{"value": [0.09167083203792573], "step": 95}]}}}, "score": 0.09203199148178101, "best_step": 95, "status": "COMPLETED", "message": null}